fabsync/__init__.py
fabsync/config.py
fabsync/files.py
fabsync/fs.py
fabsync/functools.py
fabsync/md5.sh
fabsync/py.typed
fabsync-1.2.0.dist-info/METADATA
fabsync-1.2.0.dist-info/WHEEL
fabsync-1.2.0.dist-info/licenses/UNLICENSE
fabsync-1.2.0.dist-info/RECORD
