Metadata-Version: 2.1
Name: fabsync
Version: 1.2.0
Summary: File syncing via Fabric.
Project-URL: Homepage, https://sr.ht/~psagers/fabsync/
Project-URL: Source code, https://hg.sr.ht/~psagers/fabsync
Project-URL: Documentation, https://fabsync.ignorare.net/
Author-email: Peter Sagerson <psagers@ignorare.net>
License-Expression: Unlicense
License-File: UNLICENSE
Keywords: fabric
Classifier: Development Status :: 5 - Production/Stable
Classifier: License :: OSI Approved :: The Unlicense (Unlicense)
Classifier: Programming Language :: Python :: 3
Classifier: Programming Language :: Python :: 3 :: Only
Classifier: Topic :: Utilities
Classifier: Typing :: Typed
Requires-Python: >=3.8
Requires-Dist: fabric
Requires-Dist: jsonschema~=4.5
Requires-Dist: tomli~=2.0; python_version < '3.11'
